mensuration_formulae.py
mensuration_formulae-1.6.dist-info/METADATA
mensuration_formulae-1.6.dist-info/WHEEL
mensuration_formulae-1.6.dist-info/top_level.txt
mensuration_formulae-1.6.dist-info/RECORD
